tsplit/__init__.py
tsplit/_version.py
tsplit/app_tsplit.py
tsplit/cmd_LTR.py
tsplit/cmd_TIR.py
tsplit/logs.py
tsplit/parseAlign.py
tsplit/utils.py
tsplit/wrapping.py
tsplit-0.1.4.dist-info/METADATA
tsplit-0.1.4.dist-info/WHEEL
tsplit-0.1.4.dist-info/entry_points.txt
tsplit-0.1.4.dist-info/licenses/LICENSE.txt
tsplit-0.1.4.dist-info/RECORD
