Metadata-Version: 2.4
Name: tsplit
Version: 0.1.4
Summary: Extract terminal repeats from retrotransposons (LTRs) or DNA transposons (TIRs). Compose synthetic MITES from complete DNA transposons.
Project-URL: homepage, https://github.com/adamtaranto/tSplit
Project-URL: documentation, https://github.com/adamtaranto/tSplit
Project-URL: repository, https://github.com/adamtaranto/tSplit
Author: Adam Taranto
License: MIT
License-File: LICENSE.txt
Classifier: Intended Audience :: Science/Research
Classifier: Programming Language :: Python :: 3
Classifier: Topic :: Scientific/Engineering :: Bio-Informatics
Requires-Python: >=3.8
Requires-Dist: biopython>=1.70
Requires-Dist: pymummer>=0.12.0
Requires-Dist: rich
Requires-Dist: tqdm
Provides-Extra: dev
Requires-Dist: hatch; extra == 'dev'
Requires-Dist: isort; extra == 'dev'
Requires-Dist: mkdocs; extra == 'dev'
Requires-Dist: mkdocs-jupyter; extra == 'dev'
Requires-Dist: mkdocs-material; extra == 'dev'
Requires-Dist: mkdocstrings; extra == 'dev'
Requires-Dist: mkdocstrings-python; extra == 'dev'
Requires-Dist: notebook; extra == 'dev'
Requires-Dist: numpydoc-validation; extra == 'dev'
Requires-Dist: pre-commit; extra == 'dev'
Requires-Dist: pymdown-extensions; extra == 'dev'
Requires-Dist: pytest; extra == 'dev'
Requires-Dist: pytest-cov; extra == 'dev'
Requires-Dist: ruff; extra == 'dev'
